{"incidents": [{"id": 4324270, "type": "ACCIDENT", "street": "Sierra Dr / Justin Rd", "polyline": "33.071437 -97.040462 33.072437 -97.039462", "starttime": "2025-06-25T11:14:20.890", "endtime": "2025-06-25T12:14:20.890", "description": "MAJOR ACCIDENT ON SIERRA DR", "reference": "LEWISVILLE"}, {"id": 4324287, "type": "ACCIDENT", "street": "1500 N I 35E SB", "polyline": "33.063935 -97.014782 33.064935 -97.013782", "starttime": "2025-06-25T11:32:12.373", "endtime": "2025-06-25T12:32:12.373", "description": "MAJOR ACCIDENT ON N I 35E SB", "reference": "LEWISVILLE"}]}